{
  "malema": [        
          {"id":"milho", "compra": 5.5,"venda": 8.5},
          {"id":"feijao", "compra": 5.5, "venda": 8.5},
          {"id":"arroz", "compra": 5.5,"venda": 8.5},
          {"id":"mapira", "compra": 5.5,"venda": 8.5},
          {"id":"comboio", "chegada": "8:00","partida":"8:05"}
  ],
  "mecuburi": [        
          {"id":"milho", "compra": 5.5,"venda": 8.5},
          {"id":"feijao", "compra": 5.5, "venda": 8.5},
          {"id":"arroz", "compra": 5.5,"venda": 8.5},
          {"id":"mapira", "compra": 5.5,"venda": 8.5},
          {"id":"comboio", "chegada": "8:00","partida":"8:05"}
  ],
  "gurue": [        
          {"id":"milho", "compra": 5.5,"venda": 8.5},
          {"id":"feijao", "compra": 5.5, "venda": 8.5},
          {"id":"arroz", "compra": 5.5,"venda": 8.5},
          {"id":"mapira", "compra": 5.5,"venda": 8.5},
          {"id":"comboio", "chegada": "8:00","partida":"8:05"}
  ],
  "monapo": [        
          {"id":"milho", "compra": 5.5,"venda": 8.5},
          {"id":"feijao", "compra": 5.5, "venda": 8.5},
          {"id":"arroz", "compra": 5.5,"venda": 8.5},
          {"id":"mapira", "compra": 5.5,"venda": 8.5},
          {"id":"comboio", "chegada": "8:00","partida":"8:05"}
  ]
}
